ehelply_bootstrapper/__init__.py
ehelply_bootstrapper/bootstrap.py
ehelply_bootstrapper/cli/__init__.py
ehelply_bootstrapper/cli/cli.py
ehelply_bootstrapper/drivers/__init__.py
ehelply_bootstrapper/drivers/aws.py
ehelply_bootstrapper/drivers/aws_utils/__init__.py
ehelply_bootstrapper/drivers/aws_utils/aws_apigateway.py
ehelply_bootstrapper/drivers/aws_utils/aws_asm.py
ehelply_bootstrapper/drivers/aws_utils/aws_dynamo.py
ehelply_bootstrapper/drivers/aws_utils/aws_s3.py
ehelply_bootstrapper/drivers/config.py
ehelply_bootstrapper/drivers/driver.py
ehelply_bootstrapper/drivers/fast_api.py
ehelply_bootstrapper/drivers/fast_api_utils/__init__.py
ehelply_bootstrapper/drivers/fast_api_utils/responses.py
ehelply_bootstrapper/drivers/mongo.py
ehelply_bootstrapper/drivers/mysql.py
ehelply_bootstrapper/drivers/mysql_utils/__init__.py
ehelply_bootstrapper/drivers/mysql_utils/session.py
ehelply_bootstrapper/drivers/redis.py
ehelply_bootstrapper/drivers/sentry.py
ehelply_bootstrapper/drivers/socketio.py
ehelply_bootstrapper/events/__init__.py
ehelply_bootstrapper/events/events.py
ehelply_bootstrapper/integrations/__init__.py
ehelply_bootstrapper/integrations/integration.py
ehelply_bootstrapper/models/__init__.py
ehelply_bootstrapper/models/mongo.py
ehelply_bootstrapper/models/service.py
ehelply_bootstrapper/sockets/__init__.py
ehelply_bootstrapper/sockets/backbones.py
ehelply_bootstrapper/sockets/events.py
ehelply_bootstrapper/sockets/managers.py
ehelply_bootstrapper/sockets/schemas.py
ehelply_bootstrapper/utils/__init__.py
ehelply_bootstrapper/utils/backoff.py
ehelply_bootstrapper/utils/config.py
ehelply_bootstrapper/utils/connection_details.py
ehelply_bootstrapper/utils/cryptography.py
ehelply_bootstrapper/utils/db_encryption.py
ehelply_bootstrapper/utils/docs.py
ehelply_bootstrapper/utils/dotdict.py
ehelply_bootstrapper/utils/environment.py
ehelply_bootstrapper/utils/exceptions.py
ehelply_bootstrapper/utils/in_memory_file.py
ehelply_bootstrapper/utils/releases.py
ehelply_bootstrapper-0.18.7.dist-info/entry_points.txt
ehelply_bootstrapper-0.18.7.dist-info/LICENSE
ehelply_bootstrapper-0.18.7.dist-info/WHEEL
ehelply_bootstrapper-0.18.7.dist-info/METADATA
ehelply_bootstrapper-0.18.7.dist-info/RECORD
