Metadata-Version: 2.1
Name: ehelply-bootstrapper
Version: 0.18.7
Summary: 
Home-page: https://ehelply.com
Author: Shawn Clake
Author-email: shawn.clake@gmail.com
Requires-Python: >=3.10,<3.11
Classifier: Programming Language :: Python :: 3
Classifier: Programming Language :: Python :: 3.10
Requires-Dist: GitPython (>=3.1.27,<4.0.0)
Requires-Dist: PyJWT (>=2.3.0,<3.0.0)
Requires-Dist: PyMySQL (>=1.0.2,<2.0.0)
Requires-Dist: SQLAlchemy (>=1.4.35,<2.0.0)
Requires-Dist: aiomysql (>=0.1.0,<0.2.0)
Requires-Dist: alembic (>=1.7.7,<2.0.0)
Requires-Dist: bcrypt (>=3.2.0,<4.0.0)
Requires-Dist: boto3 (>=1.21.40,<2.0.0)
Requires-Dist: cryptography (>=36.0.2,<37.0.0)
Requires-Dist: ehelply-batcher (>=1.5.0,<2.0.0)
Requires-Dist: ehelply-cacher (>=0.1.0,<0.2.0)
Requires-Dist: ehelply-logger (>=0.0.8,<0.0.9)
Requires-Dist: email-validator (>=1.1.3,<2.0.0)
Requires-Dist: fastapi (>=0.79.0,<0.80.0)
Requires-Dist: hiredis (>=2.0.0,<3.0.0)
Requires-Dist: isodate (>=0.6.1,<0.7.0)
Requires-Dist: passlib (>=1.7.4,<2.0.0)
Requires-Dist: pdoc3 (>=0.10.0,<0.11.0)
Requires-Dist: pyOpenSSL (>=22.0.0,<23.0.0)
Requires-Dist: pylint (>=2.13.5,<3.0.0)
Requires-Dist: pymlconf (>=3.0.1,<4.0.0)
Requires-Dist: pymongo (>=4.1.1,<5.0.0)
Requires-Dist: pytest-asyncio (>=0.18.3,<0.19.0)
Requires-Dist: pytest-cov (>=3.0.0,<4.0.0)
Requires-Dist: python-dateutil (>=2.8.2,<3.0.0)
Requires-Dist: python-jose (>=3.3.0,<4.0.0)
Requires-Dist: python-multipart (>=0.0.5,<0.0.6)
Requires-Dist: python-slugify (>=6.1.1,<7.0.0)
Requires-Dist: python-socketio (>=5.5.2,<6.0.0)
Requires-Dist: redis (>=4.2.2,<5.0.0)
Requires-Dist: requests (>=2.27.1,<3.0.0)
Requires-Dist: sentry-sdk[fastapi] (>=1.9.7,<2.0.0)
Requires-Dist: typer (>=0.4.1,<0.5.0)
Requires-Dist: uvicorn (>=0.17.6,<0.18.0)
Requires-Dist: wheel (>=0.37.1,<0.38.0)
